color_make/__init__.py
color_make/main.py
color_make-1.0.1.dist-info/LICENSE
color_make-1.0.1.dist-info/METADATA
color_make-1.0.1.dist-info/WHEEL
color_make-1.0.1.dist-info/entry_points.txt
color_make-1.0.1.dist-info/RECORD
