Metadata-Version: 2.1
Name: color-make
Version: 1.0.1
Summary: 
License: MIT
Author: liblaf
Author-email: i@liblaf.me
Requires-Python: >=3.11,<3.12
Classifier: License :: OSI Approved :: MIT License
Classifier: Programming Language :: Python :: 3
Classifier: Programming Language :: Python :: 3.11
Requires-Dist: rich (>=13.5.2,<14.0.0)
